webpush/__init__.py
webpush/admin.py
webpush/config.py
webpush/forms.py
webpush/jinja2.py
webpush/models.py
webpush/tests.py
webpush/urls.py
webpush/utils.py
webpush/views.py
webpush/migrations/0001_initial.py
webpush/migrations/__init__.py
webpush/static/webpush/webpush.js
webpush/templates/webpush_button.html
webpush/templates/webpush_header.html
webpush/templates/webpush_serviceworker.js
webpush/templatetags/__init__.py
webpush/templatetags/webpush_notifications.py
django_webpush_backport-0.0.1.dist-info/LICENSE
django_webpush_backport-0.0.1.dist-info/METADATA
django_webpush_backport-0.0.1.dist-info/WHEEL
django_webpush_backport-0.0.1.dist-info/top_level.txt
django_webpush_backport-0.0.1.dist-info/RECORD
